LICENSE
MANIFEST.in
README.md
setup.py
blog/__init__.py
blog/admin.py
blog/feeds.py
blog/fields.py
blog/managers.py
blog/models.py
blog/mommy_recipes.py
blog/tests.py
blog/urls.py
blog/views.py
blog/migrations/0001_initial.py
blog/migrations/0001_initial.pyc
blog/migrations/0002_auto_20141231_0859.py
blog/migrations/0002_auto_20141231_0859.pyc
blog/migrations/0003_auto_20141231_1242.py
blog/migrations/0003_auto_20141231_1242.pyc
blog/migrations/0004_entry_publicity.py
blog/migrations/0004_entry_publicity.pyc
blog/migrations/0005_entry_description.py
blog/migrations/0005_entry_description.pyc
blog/migrations/0006_auto_20160101_2343.py
blog/migrations/0006_auto_20160101_2343.pyc
blog/migrations/__init__.py
blog/migrations/__init__.pyc
blog/templates/blog/_entry.html
blog/templates/blog/blog_base.html
blog/templates/blog/entry_detail.html
blog/templates/blog/entry_list.html
blog/templates/blog/test_parent.html
blog/templatetags/__init__.py
blog/templatetags/__init__.pyc
blog/templatetags/blog_extras.py
blog/templatetags/blog_extras.pyc
blog/templatetags/markdownify.pyc
django_basic_blog.egg-info/PKG-INFO
django_basic_blog.egg-info/SOURCES.txt
django_basic_blog.egg-info/dependency_links.txt
django_basic_blog.egg-info/requires.txt
django_basic_blog.egg-info/top_level.txt